{
	 "339592807104643083": {"name": "Rashiko",             "badges": ["casualcouple", "casualcrew", "season_arms", "season_kart", "season_splat", "season_smash", "season_arms_win", "season_splat_win", "season_kart_win", "season_smash_win", "cgc", "host", "scramble", "clash", "cookoff"] }
	,"241565548318687232": {"name": "Literary",            "badges": ["casualcouple", "season_arms", "season_arms_win", "season_kart", "season_splat", "clash", "scramble", "cookoff", "cgc", "host"] }
	
	,"398284103541063690": {"name": "River",               "badges": ["clash", "clash_win"] }
	,"187272277220392960": {"name": "SlosherWailord",      "badges": ["clash", "scramble", "clash_win", "scramble_win", "season_arms"] }
	,"192081577306488842": {"name": "Serperiorfan",        "badges": ["clash", "scramble", "clash_win", "scramble_win", "season_kart", "season_smash"] }
	,"180917649444700160": {"name": "Piper",               "badges": ["clash", "scramble", "scramble_win", "cgc"] }
	
	,"378970992095264769": {"name": "Program",             "badges": ["casualcrew", "clash", "scramble", "cookoff", "cookoff_win", "season_arms", "season_kart", "season_splat", "season_smash", "cgc", "host"] }
	,"403932918466215948": {"name": "Main Main",           "badges": ["casualcrew", "clash", "scramble", "cgc", "host", "season_arms"] }
	,"215215084090294274": {"name": "Marie",               "badges": ["casualcrew", "clash", "scramble", "host", "season_arms", "season_splat", "season_splat_win"] }
	,"223927575053991936": {"name": "LandFrog",            "badges": ["casualcrew", "season_kart", "clash", "scramble"] }
	,"327864229673697290": {"name": "Cosmos",              "badges": ["casualcrew", "clash", "scramble"] }
	,"412681834493640705": {"name": "Ackus",               "badges": ["casualcrew", "clash", "host"] }
	,"186543180114690048": {"name": "Eevee",               "badges": ["casualcrew", "clash", "host"] }
	,"426780718639611905": {"name": "Fang",                "badges": ["casualcrew", "clash", "scramble", "scramble_win", "host", "season_arms", "season_splat"] }
	,"340340760698159115": {"name": "Horrible",            "badges": ["casualcrew", "host"] }
	,"164371048093974528": {"name": "GV-97",               "badges": ["host"] }
	
	,"450773792588038144": {"name": "Becca",               "badges": ["clash", "casualcrew", "scramble", "scramble_win", "season_arms", "season_splat", "season_splat_win"] }
	,"303693190932987905": {"name": "Bogalizard",          "badges": ["clash", "scramble", "season_arms", "season_arms_win", "host"] }
	,"427587118030651393": {"name": "Reis",                "badges": ["clash", "scramble", "cgc", "host", "season_arms", "season_smash"] }
	,"118794402561785857": {"name": "Toxic",               "badges": ["clash", "scramble", "season_arms", "cgc"] }
	,"312024400457236492": {"name": "Lucario",             "badges": ["clash", "scramble", "season_smash"] }
	,"311317784166531073": {"name": "Šime",                "badges": ["clash", "scramble"] }
	
	,"113030766920785920": {"name": "it's ogre",           "badges": ["clash"] }
	,"391448715103043584": {"name": "Luis",                "badges": ["clash"] }
	,"206008979430572033": {"name": "Solaris",             "badges": ["clash", "scramble", "season_smash", "season_arms"] }
	,"422305824837468170": {"name": "MJLIU",               "badges": ["clash"] }
	,"429783916342280203": {"name": "nin10taku",           "badges": ["clash", "scramble"] }
	,"272708868251844609": {"name": "Spinning",            "badges": ["clash", "host"] }
	,"347698413321584641": {"name": "Mellax",              "badges": ["clash"] }
	,"226011628389269504": {"name": "Bonlino",             "badges": ["season_kart", "clash"] }
	,"218118468401102850": {"name": "Era Wolf",            "badges": ["clash", "season_arms", "season_splat", "host"] }
	,"182639827148079106": {"name": "Buster",              "badges": ["clash", "scramble", "season_arms", "cgc"] }
	,"181858274910404608": {"name": "ThisIsRusko",         "badges": ["clash"] }
	,"275680929668792331": {"name": "Archangel-Vakarian",  "badges": ["clash"] }
	,"230829460935409664": {"name": "ailo",                "badges": ["clash"] }
	,"283783465307078656": {"name": "Juices",              "badges": ["clash", "cookoff"] }
	,"258378915133915137": {"name": "Aidan",               "badges": ["clash"] }
	
	,"178274949880872961": {"name": "StyloRen",            "badges": ["clash"] }
	,"201096122758856705": {"name": "CriticCat",           "badges": ["clash"] }
	,"267337504032555020": {"name": "FruXteN",             "badges": ["clash"] }
	,"375503052028903434": {"name": "TameDame",            "badges": ["clash"] }
	,"393525706816094209": {"name": "Flesheater",          "badges": ["clash"] }
	,"233713315304439808": {"name": "Spicy DX",            "badges": ["clash", "season_arms", "season_splat", "season_smash", "host"] }
	,"208740208768843776": {"name": "Orinetta",            "badges": ["clash"] }
	,"258098427844493316": {"name": "Sora",                "badges": ["clash", "scramble", "cookoff", "season_arms", "season_smash", "host", "season_splat"] }
	,"269980957212147714": {"name": "Mario119",            "badges": ["clash"] }
	,"231574706506039298": {"name": "RickHardslab",        "badges": ["clash"] }
	,"191293552142057473": {"name": "Kat",                 "badges": ["clash", "scramble"] }
	,"211794202370113536": {"name": "Levi",                "badges": ["clash", "scramble", "cgc", "season_arms", "season_kart", "season_smash", "host"] }
	,"415266965788295168": {"name": "Dendrimer",           "badges": ["clash"] }
	,"333469682952830976": {"name": "ai-chan",             "badges": ["clash"] }
	,"353673806008549377": {"name": "Hamma",               "badges": ["clash"] }
	,"221495328497467392": {"name": "Cocovet",             "badges": ["clash", "casualcrew", "scramble", "season_arms_win", "season_arms", "season_smash", "season_smash_win"] }
	,"213547862523379712": {"name": "KegMinami",           "badges": ["clash"] }
	,"339645959610826752": {"name": "Comet",               "badges": ["clash"] }
	,"109484254517293056": {"name": "Drift",               "badges": ["clash", "scramble"] }
	,"272505335812456449": {"name": "Raffa",               "badges": ["clash", "scramble"] }
	,"366185416581447690": {"name": "Ripha",               "badges": ["clash"] }
	,"322774612712620033": {"name": "Spronch",             "badges": ["clash"] }
	,"265580646162890756": {"name": "eonia",               "badges": ["clash", "scramble"] }
	,"328620607119949825": {"name": "ChioZa",              "badges": ["clash"] }
	
	,"226824104399994881": {"name": "lilbeansie",          "badges": ["scramble", "season_splat"] }
	,"208664924145188866": {"name": "Idranoid",            "badges": ["scramble"] }
	,"576548421494898698": {"name": "Anubis",              "badges": ["season_arms"] }
	
	,"315301009117413376": {"name": "GM-Tom",              "badges": ["casualcrew", "season_arms", "season_arms_win", "season_splat", "season_smash", "season_smash_win", "clash", "scramble"] }
	,"308818549655339008": {"name": "E.P.Silon",           "badges": ["cgc"] }
	,"398013985619968010": {"name": "idkhonestly",         "badges": ["cgc"] }
	,"302855132431777792": {"name": "Jake",                "badges": ["cgc", "season_arms", "season_kart", "season_splat", "season_smash", "scramble", "host"] }
	,"449596679218266112": {"name": "Spenjo",              "badges": ["cgc", "host", "season_arms", "season_kart", "clash", "scramble"] }
	
	,"196169851788591104": {"name": "Jiko",                "badges": ["clash", "scramble"] }
	,"327106519785275392": {"name": "SirRacha",            "badges": ["cgc", "clash", "scramble", "season_arms"] }
	,"136779908910153728": {"name": "IncredibleMeh",       "badges": ["scramble"] }
	,"140236006380142592": {"name": "ShinySP",             "badges": ["scramble"] }
	,"430764831927304193": {"name": "Mr.MGamer",           "badges": ["season_arms", "season_kart", "season_smash", "clash", "scramble"] }
	,"350461137357242368": {"name": "FuzMustard",          "badges": ["scramble"] }
	
	,"417021831854292992": {"name": "JoyJaz",              "badges": ["host"] }
	,"158902691542597632": {"name": "taste!",              "badges": ["host"] }
	,"137185743654223873": {"name": "Camryn",              "badges": ["host"] }
	,"136343819829510145": {"name": "tehbs",               "badges": ["host"] }
	,"275680929668792331": {"name": "Archangel-V.",        "badges": ["host"] }
	
	,"382484155822243842": {"name": "mattatthat",          "badges": ["clash"] }
	,"249430453751250945": {"name": "Asqew",               "badges": ["clash", "clash_win"] }
	,"396420455545831425": {"name": "C-smax",              "badges": ["clash", "scramble"] }
	,"389920535653515264": {"name": "Ruction",             "badges": ["clash"] }
	,"86282152777367552":  {"name": "Mileve",              "badges": ["clash", "scramble"] }
	,"196390864543678464": {"name": "Mogori",              "badges": ["clash"] }
	,"350643816404877322": {"name": "Sam (BunnyChamp)",    "badges": ["clash", "clash_win", "scramble", "season_arms", "season_splat"] }
	,"219155908830298132": {"name": "Uran",                "badges": ["season_kart", "season_smash", "clash", "clash_win", "scramble", "scramble_win", "cookoff"] }
	,"265719610681065472": {"name": "CheezLuigi",          "badges": ["season_arms", "clash", "scramble", "scramble_win"] }
	,"508809343597281305": {"name": "GlitchWork",          "badges": ["season_arms"] }
	,"464467971574595585": {"name": "Goomba",              "badges": ["season_arms", "season_kart", "season_splat", "season_smash", "season_splat_win", "clash", "scramble", "cookoff", "cookoff_win", "host"] }
	,"207741284050403328": {"name": "Geeligan",            "badges": ["season_kart"] }
	
	,"138729882556301313": {"name": "Dendy",               "badges": ["scramble"] }
	,"196399844988813312": {"name": "Boop",                "badges": ["scramble"] }
	,"381626947119218699": {"name": "Beamer",              "badges": ["clash", "scramble", "clash_win", "scramble_win"] }
	
	,"196380470177562625": {"name": "Gote",                "badges": ["clash", "scramble", "season_arms", "season_kart", "season_splat", "season_kart_win", "season_smash", "cgc", "host"] }
	,"163427256264425472": {"name": "Xelor41023",          "badges": ["scramble"] }
	,"164685995583733760": {"name": "AntheM",              "badges": ["scramble", "scramble_win"] }
	,"266330502439370752": {"name": "kilian_smt",          "badges": ["scramble"] }
	,"518513221561352213": {"name": "creamerpm",           "badges": ["scramble"] }
	
	,"443737601904476160": {"name": "Buch",                "badges": ["clash"] }
	,"243190204771336192": {"name": "Hennessey",           "badges": ["clash"] }
	,"263368462745862144": {"name": "DeadBOI",             "badges": ["clash", "season_splat"] }
	,"294963125591998466": {"name": "Sintha",              "badges": ["clash", "season_kart"] }
	,"329034278803472394": {"name": "Fish",                "badges": ["clash", "scramble"] }
	,"523864053542682624": {"name": "5after12",            "badges": ["clash", "scramble", "season_arms"] }
	,"458379136621084673": {"name": "JBPro",               "badges": ["clash", "clash_win"] }
	
	,"491050652978511873": {"name": "9nineLives",          "badges": ["scramble"] }
	,"272037378749628428": {"name": "yver20",              "badges": ["scramble", "clash"] }
	,"207244940667781120": {"name": "Nathan",              "badges": ["scramble"] }
	,"277470404166287371": {"name": "Paradox",             "badges": ["season_kart"] } 
	,"165048408518819840": {"name": "Nowi",	             "badges": ["season_kart"] } 
	,"347435736598970369": {"name": "Nylis",               "badges": ["season_kart"] }
	,"411789586495438858": {"name": "LesFleur",            "badges": ["season_arms", "clash"] }
	
	,"131597700884856832": {"name": "noahlot",             "badges": ["scramble"] }
	,"183043875580018688": {"name": "Kon",                 "badges": ["scramble", "clash", "cookoff"] }
	,"409578580209827841": {"name": "Dory",                "badges": ["scramble", "clash"] }
	,"257959389594386433": {"name": "HKGamer13",           "badges": ["scramble"] }
	
	,"330563262141825024": {"name": "Sadaly",              "badges": ["season_arms", "season_kart", "season_kart_win", "season_splat"] }
	,"81084716635131904":  {"name": "Pikscast",            "badges": ["host", "season_kart", "season_splat", "season_smash"] }
	,"422156668411838465": {"name": "Sarahy",              "badges": ["season_kart", "season_splat", "season_splat_win"] }
	,"134117027802644490": {"name": "Abrams",              "badges": ["season_kart"] }
	,"292535803262009346": {"name": "Gabstriel",           "badges": ["season_splat", "cookoff"] }
	,"142716556340756481": {"name": "Pawl",                "badges": ["host", "season_splat", "season_smash", "clash", "cookoff"] }
	,"400479213817298946": {"name": "The Oddity",          "badges": ["host", "season_kart", "season_splat", "season_smash", "cookoff"] }

	,"111446699360202752": {"name": "Chyro",               "badges": ["clash", "clash_win"] }
	,"145375063724654592": {"name": "Mig",                 "badges": ["clash", "scramble"] }
	,"220859634737610752": {"name": "BackpackTV",          "badges": ["clash"] }
	,"454438240708067328": {"name": "Patita",              "badges": ["season_arms", "season_smash", "clash", "scramble"] }
	,"431095641226215434": {"name": "Claro0602",           "badges": ["clash"] }
	,"530944778867572737": {"name": "MrWLG",               "badges": ["scramble"] }
	
	,"340257118298832945": {"name": "Mindy (WhisperingShadow)", "badges": ["season_arms"] }
	,"238976648471511041": {"name": "VerteX",              "badges": ["season_kart", "season_kart_win"] }
	
	,"410828670874419211": {"name": "wa",                  "badges": ["clash", "clash_win", "scramble", "scramble_win", "season_arms"] }
	,"553998647994482731": {"name": "MD",                  "badges": ["clash"] }
	,"124936014044069891": {"name": "Penzo",               "badges": ["clash"] }
	
	,"290859892330332161": {"name": "Louise",              "badges": ["scramble"] }
	,"556797345803665438": {"name": "lavender",            "badges": ["scramble"] }
	
	,"240784844462882816": {"name": "Summerwind",          "badges": ["season_kart"] }
	,"229991858229477377": {"name": "Steelhead",           "badges": ["season_kart"] }
	,"339632593081335809": {"name": "Lucario",             "badges": ["season_kart", "season_splat"] }
	,"540331615088541705": {"name": "Kkarbon",             "badges": ["season_arms", "season_kart", "season_splat", "clash"] }
	
	,"220949713447288832": {"name": "Panthermon",          "badges": ["season_splat", "season_smash", "scramble", "clash"] }
	,"257269741817823235": {"name": "snipEZ",              "badges": ["season_splat"] }
	,"401610413441024020": {"name": "Randowo",             "badges": ["scramble"] }
	,"147364668359442432": {"name": "Ceipe007",            "badges": ["season_splat"] }
	
	,"214222499066544138": {"name": "Gomi",                "badges": ["clash", "season_smash"] }
	,"325240362237034499": {"name": "midonnay",            "badges": ["clash"] }
	,"300694579563331584": {"name": "Tree",                "badges": ["clash"] }

	,"280445025437876224": {"name": "BBoverkill",          "badges": ["scramble"] }
	,"403186564944887808": {"name": "Ash",                 "badges": ["scramble"] }
	
	,"422871705736970240": {"name": "Payohloh",            "badges": ["season_arms", "clash", "scramble", "cookoff"] }
	,"314520913452335105": {"name": "aBean (82)",          "badges": ["season_splat", "clash", "scramble"] }
	,"476100985408716837": {"name": "JokingHazard",        "badges": ["season_smash"] }
	,"341925381042864130": {"name": "Morpheus",            "badges": ["season_smash"] }
	
	,"438314123399397376": {"name": "Teriaqi",             "badges": ["clash"] }
	
	,"162257115413610496": {"name": "Juice",               "badges": ["scramble", "season_splat"] }
	,"342275923434930186": {"name": "Morbol",              "badges": ["scramble"] }
	,"337665120115228674": {"name": "Jorr",                "badges": ["scramble", "clash"] }
	
	,"284382528536838154": {"name": "Pineapple",           "badges": ["clash", "clash_win"] }
	,"132625817351094272": {"name": "supercheese",         "badges": ["clash"] }
	,"320624699094597642": {"name": "MrSerket",            "badges": ["clash"] }
	,"128611839574671360": {"name": "SpectralDynamite",    "badges": ["clash"] }
	,"281822770395086848": {"name": "MeltyMetroid",        "badges": ["clash"] }
	,"180791697125408768": {"name": "Dock",                "badges": ["season_splat", "cookoff"] }
	,"234500747020992515": {"name": "Donkat",              "badges": ["season_splat"] }
	,"461326246576390147": {"name": "Vodka",               "badges": ["season_smash"] }
	,"331214369910161408": {"name": "Salad",               "badges": ["season_smash"] }
	
	,"316387447317463041": {"name": "LAB",                 "badges": ["clash"] }
	,"187236610046164992": {"name": "Cosalina",            "badges": ["clash"] }
	,"460862593616183317": {"name": "squidy",              "badges": ["clash", "scramble", "season_arms", "season_splat", "season_smash"] }
	,"449213504537231360": {"name": "DinosaurY",           "badges": ["season_smash", "season_splat", "cookoff"] }  
	
	,"144138362226343936": {"name": "Udon",                "badges": ["scramble", "clash", "season_arms", "season_splat", "cookoff"] }
	,"154431224939675648": {"name": "Radio",               "badges": ["scramble"] }
	,"174558464230686720": {"name": "Gryffical",           "badges": ["scramble", "scramble_win"] }
	
	,"238698278290456581": {"name": "Grimwood",            "badges": ["season_arms"] }
	
	,"539831517262905365": {"name": "Solace",               "badges": ["clash"] }
	,"301519653602197505": {"name": "Natty",                "badges": ["clash"] }
	,"207394564988731393": {"name": "SanicBoom4",           "badges": ["clash"] }
	,"333804452475830277": {"name": "Penzo",                "badges": ["clash"] }
}
