[
	 {"titleText":"Standard Saturday!","type":0,"theme":"everything","date":"2018-11-10T19:00:00.000Z","duration":120,"timeZone":"EST","hosts":[{"name":"Rashiko","tag":"CC","code":"6822-5055-2423","tier":0},{"name":"Spenjo","tag":"","code":"0725-4824-1895","tier":0}],"streamers":[]}
	,{"titleText":"CotE Warmup","type":4,"theme":"cote","date":"2018-11-11T21:45:00.000Z","duration":60,"timeZone":"EST","hosts":[{"name":"Literary","tag":"","code":"4704-7597-7783","tier":0},{"name":"Program","tag":"","code":"4898-5196-4000","tier":0}],"streamers":[]}
	,{"titleText":"MLM Warmup","type":3,"theme":"mlm","date":"2018-11-12T21:45:00.000Z","duration":60,"timeZone":"EST","hosts":[{"name":"Mileve","tag":"","code":"2795-2096-7893","tier":0},{"name":"Spenjo","tag":"","code":"0725-4824-1895","tier":0}],"streamers":["mileve"]}
	,{"titleText":"Tidal Tuesday","type":0,"theme":"breakable-bits","date":"2018-11-14T02:00:00.000Z","duration":120,"timeZone":"PST","hosts":[{"name":"Sora","tag":"","code":"0499-4528-8293","tier":0}],"streamers":["sorafirestorm"]}
	,{"titleText":"Wildcard Wednesday","type":0,"theme":"teambuilding-near-far","date":"2018-11-14T23:00:00.000Z","duration":120,"timeZone":"EST","hosts":[{"name":"Rashiko","tag":"CC","code":"6822-5055-2423","tier":0},{"name":"Spenjo","tag":"","code":"0725-4824-1895","tier":0}],"streamers":[]}
	,{"titleText":"Thumpin' Thursday","type":0,"theme":"fights-only","date":"2018-11-15T19:00:00.000Z","duration":120,"timeZone":"GMT","hosts":[{"name":"Rashiko","tag":"CC","code":"6822-5055-2423","tier":0}],"streamers":[]}
	,{"titleText":"Casual Clash 7","type":2,"theme":"clash","date":"2018-11-17T21:30:00.000Z","duration":90,"timeZone":"EST","hosts":[],"streamers":[]}
	,{"titleText":"Clash Warmup","type":1,"theme":"clash","date":"2018-11-17T20:15:00.000Z","duration":60,"timeZone":"EST","hosts":[{"name":"Rashiko","tag":"CC","code":"6822-5055-2423","tier":0},{"name":"Literary","tag":"","code":"4704-7597-7783","tier":0}],"streamers":[]}
	,{"titleText":"Mario Kart 8 DX Event","type":6,"theme":"undefined","date":"2018-11-18T00:00:00.000Z","duration":120,"timeZone":"EST","hosts":[{"name":"","tag":"","code":"4412-5645-5723","tier":0}],"streamers":[]}
	,{"titleText":"CotE Warmup","type":4,"theme":"cote","date":"2018-11-18T21:45:00.000Z","duration":60,"timeZone":"EST","hosts":[{"name":"Program","tag":"","code":"4898-5196-4000","tier":0}],"streamers":[]}	,{"titleText":"Mario Kart 8 DX Event","type":6,"theme":"undefined","date":"2018-11-19T19:00:00.000Z","duration":120,"timeZone":"EST","hosts":[{"name":"","tag":"","code":"1077-9421-4443","tier":0}],"streamers":[]}
	,{"titleText":"MLM Warmup","type":3,"theme":"mlm","date":"2018-11-19T21:45:00.000Z","duration":60,"timeZone":"EST","hosts":[{"name":"Literary","tag":"","code":"4704-7597-7783","tier":0},{"name":"Mileve","tag":"","code":"2795-2096-7893","tier":0}],"streamers":["mileve"]}
	,{"titleText":"Tidal Tuesday","type":0,"theme":"teambuilding-near-far","date":"2018-11-21T02:00:00.000Z","duration":120,"timeZone":"PST","hosts":[{"name":"Marie","tag":"CC","code":"5693-4645-2698","tier":0},{"name":"Literary","tag":"","code":"4704-7597-7783","tier":0}],"streamers":[]}
	,{"titleText":"Wildcard Wednesday","type":0,"theme":"teambuilding","date":"2018-11-21T23:00:00.000Z","duration":120,"timeZone":"EST","hosts":[{"name":"Literary","tag":"","code":"4704-7597-7783","tier":0},{"name":"Rashiko","tag":"CC","code":"6822-5055-2423","tier":0}],"streamers":[]}
	,{"titleText":"Mario Kart 8 DX Event","type":6,"theme":"undefined","date":"2018-11-26T19:00:00.000Z","duration":120,"timeZone":"EST","hosts":[{"name":"","tag":"","code":"1077-9421-4443","tier":0}],"streamers":[]}
	,{"titleText":"Mario Kart 8 DX Event","type":6,"theme":"undefined","date":"2018-11-28T19:00:00.000Z","duration":120,"timeZone":"EST","hosts":[{"name":"","tag":"","code":"4621-2901-6363","tier":0}],"streamers":[]}
	,{"titleText":"Mario Kart 8 DX Event","type":6,"theme":"undefined","date":"2018-11-21T19:00:00.000Z","duration":120,"timeZone":"EST","hosts":[{"name":"","tag":"","code":"4621-2901-6363","tier":0}],"streamers":[]}
	,{"titleText":"Mario Kart 8 DX Event","type":6,"theme":"undefined","date":"2018-11-25T00:00:00.000Z","duration":120,"timeZone":"EST","hosts":[{"name":"","tag":"","code":"4412-5645-5723","tier":0}],"streamers":[]}
	,{"titleText":"MLM Warmup","type":3,"theme":"mlm","date":"2018-11-26T21:45:00.000Z","duration":60,"timeZone":"EST","hosts":[{"name":"Literary","tag":"","code":"4704-7597-7783","tier":0},{"name":"Mileve","tag":"","code":"2795-2096-7893","tier":0}],"streamers":["mileve"]}
	,{"titleText":"Tidal Tuesday","type":0,"theme":"corner-chaos","date":"2018-11-28T02:00:00.000Z","duration":120,"timeZone":"PST","hosts":[{"name":"Rashiko","tag":"CC","code":"6822-5055-2423","tier":0},{"name":"Sora","tag":"","code":"0499-4528-8293","tier":0}],"streamers":["sorafirestorm"]}
	,{"titleText":"Wildcard Wednesday","type":0,"theme":"hedlok-havok","date":"2018-11-28T23:00:00.000Z","duration":120,"timeZone":"EST","hosts":[{"name":"Marie","tag":"CC","code":"5693-4645-2698","tier":0},{"name":"Rashiko","tag":"CC","code":"6822-5055-2423","tier":0}],"streamers":[]}
	,{"titleText":"Thumpin' Thursday","type":0,"theme":"fights-only","date":"2018-11-29T19:00:00.000Z","duration":120,"timeZone":"GMT","hosts":[{"name":"Rashiko","tag":"CC","code":"6822-5055-2423","tier":0},{"name":"GV-97","tag":"","code":"5861-0816-5793","tier":0}],"streamers":[]}
	,{"titleText":"Casual Scramble Warmup","type":1,"theme":"scramble","date":"2018-12-01T20:15:00.000Z","duration":60,"timeZone":"EST","hosts":[{"name":"Rashiko","tag":"CC","code":"6822-5055-2423","tier":0},{"name":"Eevee","tag":"","code":"1703-8817-5789","tier":0}],"streamers":[],"sponsor":"mindgames"}
	,{"titleText":"Casual Scramble 4","type":5,"theme":"scramble","date":"2018-12-01T21:30:00.000Z","duration":120,"timeZone":"EST","hosts":[],"streamers":[],"sponsor":"mindgames"}
	,{"titleText":"CotE Warmup","type":4,"theme":"cote","date":"2018-11-25T21:45:00.000Z","duration":60,"timeZone":"EST","hosts":[{"name":"Literary","tag":"","code":"4704-7597-7783","tier":0}],"streamers":[]}
	
	,{"titleText":"Sunday Showdown","type":0,"theme":"everything","date":"2018-12-02T20:45:00.000Z","duration":120,"timeZone":"EST","hosts":[{"name":"Marie","tag":"CC","code":"5693-4645-2698","tier":0},{"name":"Literary","tag":"","code":"4704-7597-7783","tier":0}],"streamers":[]}
	,{"titleText":"Mario Kart 8 DX Event","type":6,"theme":"undefined","date":"2018-12-02T00:00:00.000Z","duration":120,"timeZone":"EST","hosts":[{"name":"","tag":"","code":"4412-5645-5723","tier":0}],"streamers":[]}
	,{"titleText":"Mario Kart 8 DX Event","type":6,"theme":"undefined","date":"2018-12-03T19:00:00.000Z","duration":120,"timeZone":"EST","hosts":[{"name":"","tag":"","code":"1077-9421-4443","tier":0}],"streamers":[]}
	,{"titleText":"MLM Warmup","type":3,"theme":"mlm","date":"2018-12-03T21:45:00.000Z","duration":60,"timeZone":"EST","hosts":[{"name":"To Be Announced","tag":"","code":"-","tier":0}],"streamers":[]}
	,{"titleText":"Tidal Tuesday","type":0,"theme":"everything","date":"2018-12-05T02:00:00.000Z","duration":120,"timeZone":"PST","hosts":[{"name":"To Be Announced","tag":"","code":"-","tier":0}],"streamers":[]}
	,{"titleText":"Mario Kart 8 DX Event","type":6,"theme":"undefined","date":"2018-12-05T19:00:00.000Z","duration":120,"timeZone":"EST","hosts":[{"name":"","tag":"","code":"4621-2901-6363","tier":0}],"streamers":[]}
	,{"titleText":"Wildcard Wednesday","type":0,"theme":"breakable-bits","date":"2018-12-05T23:00:00.000Z","duration":120,"timeZone":"EST","hosts":[{"name":"To Be Announced","tag":"","code":"-","tier":0}],"streamers":[]}
	,{"titleText":"Thumpin' Thursday","type":0,"theme":"fights-only","date":"2018-12-06T19:00:00.000Z","duration":120,"timeZone":"GMT","hosts":[{"name":"To Be Announced","tag":"","code":"-","tier":0}],"streamers":[]}
	
	
	
	
	,{"titleText":"Casual Clash 6","type":2,"theme":"clash","date":"2018-10-20T20:30:00.000Z","duration":90,"timeZone":"EDT","hosts":[]}
	,{"titleText":"Casual Scramble 3","type":5,"theme":"scramble","date":"2018-11-03T20:30:00.000Z","duration":90,"timeZone":"EDT","hosts":[],"streamers":[],"sponsor":"mindgames"}
	
	
]
